[
  {
    "id": "ip",
    "label": "Address",
    "type": "text",
    "default": "localhost"
  },
  {
    "id": "port",
    "label": "Port Number",
    "type": "text",
    "default": "8989"
  },
  {
    "id": "base",
    "label":  "URL Base (ex. /sonarr)",
    "type": "text",
    "default": ""
  },
  {
    "id": "https",
    "label": "Enable SSL",
    "type": "bool",
    "default": "false"
  },
  {
    "id": "apiKey",
    "label": "API Key (Required)",
    "type": "text",
    "default": ""
  },
  {
    "id": "username",
    "label": "Username",
    "type": "text",
    "default": ""
  },
  {
    "id": "password",
    "label": "Password",
    "type": "text",
    "option": "hidden",
    "default": "",
    "secure": "true"
  },
  {
    "id": "auth",
    "label": "Authentication",
    "type": "enum",
    "values": ["None", "Basic", "Digest"],
    "default": "None"
  },
  {
    "id": "season_folder",
    "label": "Use season folders (when adding series)",
    "type": "bool",
    "default": "true"
  },
  {
    "id": "delete_files",
    "label": "Delete files permanently from disk when removing episodes",
    "type": "bool",
    "default": "false"
  }
]
